{
    "hand_decision" : "What would you like to do? (hit/stand/double down/split): ",
    "bet" : "please enter a bet: ",
    "seat" : "Which seat would you like to sit at?: ",
    "table" : "Which table would you like to check out? ",
    "profile" : "Type the number of the profile you would like to use? Type 'new' to create a new profile: ",
    "invalid_list_input" : "Please enter a valid number from the provided list",
    "invalid_bet_input" : "Your bet must be a whole number: ",
    "insufficient_money" : "You do not have enough money to bet this amount"

}